gemseo_mma/__init__.py
gemseo_mma/opt/__init__.py
gemseo_mma/opt/mma.py
gemseo_mma/opt/mma_settings.py
gemseo_mma/opt/core/__init__.py
gemseo_mma/opt/core/mma.py
gemseo_mma/opt/core/mma_optimizer.py
gemseo_mma-4.0.0.dist-info/licenses/LICENSE.txt
gemseo_mma-4.0.0.dist-info/METADATA
gemseo_mma-4.0.0.dist-info/WHEEL
gemseo_mma-4.0.0.dist-info/entry_points.txt
gemseo_mma-4.0.0.dist-info/top_level.txt
gemseo_mma-4.0.0.dist-info/RECORD
